LICENSE
MANIFEST.in
README.md
requirements.txt
setup.cfg
setup.py
sgmarkets_api_auth/__init__.py
sgmarkets_api_auth/__meta__.py
sgmarkets_api_auth/api_v1.py
sgmarkets_api_auth/api_v2.py
sgmarkets_api_auth/util.py
sgmarkets_api_auth.egg-info/PKG-INFO
sgmarkets_api_auth.egg-info/SOURCES.txt
sgmarkets_api_auth.egg-info/dependency_links.txt
sgmarkets_api_auth.egg-info/not-zip-safe
sgmarkets_api_auth.egg-info/requires.txt
sgmarkets_api_auth.egg-info/top_level.txt
sgmarkets_api_auth/img/sg-research-logo-displayed.png
sgmarkets_api_auth/img/sg-sgmarkets-logo.png
sgmarkets_api_auth/sample/my_secret.tpl.txt
sgmarkets_api_auth/sample/my_secret_v1.txt