Metadata-Version: 1.1
Name: sgmarkets-api-auth
Version: 0.3.0
Summary: sgmarket api authentication
Home-page: https://gitlab.com/sgmarkets/sgmarkets-api-auth
Author: sgmarkets
Author-email: olivier.borderies@gmail.com
License: MIT
Download-URL: https://gitlab.com/sgmarkets/sgmarkets-api-auth/repository/archive.tar.gz?ref=0.3.0
Keywords: sgmarkets,api,authentication
Platform: UNKNOWN
Classifier: Development Status :: 4 - Beta
Classifier: License :: OSI Approved :: MIT License
Classifier: Programming Language :: Python :: 3.5
Classifier: Programming Language :: Python :: 3.6
